physiossl/__init__.py
physiossl/backbone/__init__.py
physiossl/backbone/encoder.py
physiossl/backbone/mlp.py
physiossl/backbone/recurrent.py
physiossl/backbone/transformer.py
physiossl/data/__init__.py
physiossl/data/feature_extraction.py
physiossl/data/preprocessing.py
physiossl/datasets/__init__.py
physiossl/datasets/amigos.py
physiossl/datasets/bciciv2.py
physiossl/datasets/deap.py
physiossl/datasets/isruc.py
physiossl/datasets/opportunity.py
physiossl/datasets/sleepedf.py
physiossl/datasets/utils.py
physiossl/datasets/wrapper.py
physiossl/dist/__init__.py
physiossl/dist/utils.py
physiossl/evaluation/__init__.py
physiossl/evaluation/instance_retrieval.py
physiossl/evaluation/linear_classification.py
physiossl/evaluation/semi_supervised_classification.py
physiossl/evaluation/transfer_learning.py
physiossl/evaluation/transferring_features.py
physiossl/evaluation/utils.py
physiossl/learning/__init__.py
physiossl/learning/moco_infonce_loss.py
physiossl/learning/simclr_infonce_loss.py
physiossl/learning/soft_logit_loss.py
physiossl/learning/sup_contras_loss.py
physiossl/learning/triplet_loss.py
physiossl/models/__init__.py
physiossl/models/cosleep.py
physiossl/models/cpc.py
physiossl/models/dcc.py
physiossl/models/discriminativecontrastivecoding.py
physiossl/models/dpc.py
physiossl/models/dpcm.py
physiossl/models/moco.py
physiossl/models/rp.py
physiossl/models/simclr.py
physiossl/models/tcl.py
physiossl/models/tloss.py
physiossl/models/tnc.py
physiossl/models/ts.py
physiossl/models/tstcc.py
physiossl/training/__init__.py
physiossl/training/utils.py
physiossl/transforms/__init__.py
physiossl/transforms/functional.py
physiossl/transforms/transforms.py
physiossl/utils/__init__.py
test/__init__.py
test/test_dataset.py
test/test_datasets.py
test/test_encoder.py
test/test_simclr_infonce_loss.py
test/test_sleepedf.py
physiossl-0.0.1a2.dist-info/LICENSE
physiossl-0.0.1a2.dist-info/METADATA
physiossl-0.0.1a2.dist-info/WHEEL
physiossl-0.0.1a2.dist-info/top_level.txt
physiossl-0.0.1a2.dist-info/RECORD
