Metadata-Version: 2.1
Name: physiossl
Version: 0.0.1a2
Summary: PhysioSSL: A Python Toolbox for Physiological Time-series Representation Learning
Home-page: https://github.com/larryshaw0079/PhysioSSL
Author: qinfeng xiao
Author-email: qfxiao@bjtu.edu.cn
License: MIT license
Platform: UNKNOWN
Requires-Python: >=3.6
License-File: LICENSE
Requires-Dist: numpy
Requires-Dist: pandas
Requires-Dist: scipy (>=0.14.0)
Requires-Dist: matplotlib
Requires-Dist: scikit-learn (>=0.22.1)
Requires-Dist: torch (>=1.6)
Requires-Dist: pyadts
Requires-Dist: tqdm
Requires-Dist: einops
Requires-Dist: pyts (>=0.11.0)
